NLPreprocessor/Preprocessing.py
NLPreprocessor/__init__.py
NLPreprocessor-0.1.dist-info/METADATA
NLPreprocessor-0.1.dist-info/WHEEL
NLPreprocessor-0.1.dist-info/top_level.txt
NLPreprocessor-0.1.dist-info/RECORD
