Metadata-Version: 2.1
Name: NLPreprocessor
Version: 0.1
Summary: Basic Preprocessor for NLP 
Home-page: UNKNOWN
Author: Mathew Mammen Jacob
Author-email: <mathew.mammenjacob@gmail.com>
License: UNKNOWN
Keywords: python,Second package,NLP
Platform: UNKNOWN
Classifier: Development Status :: 3 - Alpha
Classifier: Intended Audience :: Education
Classifier: Programming Language :: Python :: 2
Classifier: Programming Language :: Python :: 3
Classifier: Operating System :: MacOS :: MacOS X
Classifier: Operating System :: Microsoft :: Windows
Requires-Dist: NLTK
